PyCVMeasure
